thpham/cdk_developer_tools_notifications/__init__.py
thpham/cdk_developer_tools_notifications/py.typed
thpham/cdk_developer_tools_notifications/_jsii/__init__.py
thpham/cdk_developer_tools_notifications/_jsii/cdk-developer-tools-notifications@2.3.1.jsii.tgz
thpham.cdk_developer_tools_notifications-2.3.1.dist-info/LICENSE
thpham.cdk_developer_tools_notifications-2.3.1.dist-info/METADATA
thpham.cdk_developer_tools_notifications-2.3.1.dist-info/WHEEL
thpham.cdk_developer_tools_notifications-2.3.1.dist-info/top_level.txt
thpham.cdk_developer_tools_notifications-2.3.1.dist-info/RECORD
