Metadata-Version: 2.1
Name: thpham.cdk-developer-tools-notifications
Version: 2.3.1
Summary: #slack / msteams / email notifications for developer tools: CodeCommit, CodeBuild, CodeDeploy, CodePipeline
Home-page: https://github.com/thpham/cdk-constructs
Author: thpham
License: MIT
Project-URL: Source, https://github.com/thpham/cdk-constructs.git
Classifier: Intended Audience :: Developers
Classifier: Operating System :: OS Independent
Classifier: Programming Language :: JavaScript
Classifier: Programming Language :: Python :: 3 :: Only
Classifier: Programming Language :: Python :: 3.8
Classifier: Programming Language :: Python :: 3.9
Classifier: Programming Language :: Python :: 3.10
Classifier: Programming Language :: Python :: 3.11
Classifier: Typing :: Typed
Classifier: License :: OSI Approved
Requires-Python: ~=3.8
License-File: LICENSE
Requires-Dist: aws-cdk-lib <3.0.0,>=2.141.0
Requires-Dist: constructs <11.0.0,>=10.3.0
Requires-Dist: jsii <2.0.0,>=1.95.0
Requires-Dist: publication >=0.0.3
Requires-Dist: thpham.cdk-chatops <3.0.0,>=2.3.0
Requires-Dist: typeguard ~=2.13.3
